odoo/addons/vendor_transport_lead_time/README.rst
odoo/addons/vendor_transport_lead_time/__init__.py
odoo/addons/vendor_transport_lead_time/__manifest__.py
odoo/addons/vendor_transport_lead_time/i18n/es.po
odoo/addons/vendor_transport_lead_time/i18n/it.po
odoo/addons/vendor_transport_lead_time/i18n/pt_BR.po
odoo/addons/vendor_transport_lead_time/i18n/vendor_transport_lead_time.pot
odoo/addons/vendor_transport_lead_time/models/__init__.py
odoo/addons/vendor_transport_lead_time/models/product_supplierinfo.py
odoo/addons/vendor_transport_lead_time/models/purchase_order_line.py
odoo/addons/vendor_transport_lead_time/readme/CONTRIBUTORS.md
odoo/addons/vendor_transport_lead_time/readme/CREDITS.md
odoo/addons/vendor_transport_lead_time/readme/DESCRIPTION.md
odoo/addons/vendor_transport_lead_time/readme/HISTORY.md
odoo/addons/vendor_transport_lead_time/report/purchase_order_template.xml
odoo/addons/vendor_transport_lead_time/static/description/icon.png
odoo/addons/vendor_transport_lead_time/static/description/index.html
odoo/addons/vendor_transport_lead_time/tests/__init__.py
odoo/addons/vendor_transport_lead_time/tests/test_delay.py
odoo/addons/vendor_transport_lead_time/tests/test_purchase_order.py
odoo/addons/vendor_transport_lead_time/views/product_supplierinfo.xml
odoo/addons/vendor_transport_lead_time/views/purchase_order_line.xml
odoo_addon_vendor_transport_lead_time-18.0.1.0.1.1.dist-info/METADATA
odoo_addon_vendor_transport_lead_time-18.0.1.0.1.1.dist-info/WHEEL
odoo_addon_vendor_transport_lead_time-18.0.1.0.1.1.dist-info/top_level.txt
odoo_addon_vendor_transport_lead_time-18.0.1.0.1.1.dist-info/RECORD
